fibery_mcp_server/__init__.py
fibery_mcp_server/__main__.py
fibery_mcp_server/fibery_client.py
fibery_mcp_server/server.py
fibery_mcp_server/utils.py
fibery_mcp_server/tools/__init__.py
fibery_mcp_server/tools/create_entities_batch.py
fibery_mcp_server/tools/create_entity.py
fibery_mcp_server/tools/current_date.py
fibery_mcp_server/tools/database.py
fibery_mcp_server/tools/query.py
fibery_mcp_server/tools/schema.py
fibery_mcp_server/tools/update_entity.py
fibery_mcp_server/tools/descriptions/create_entities_batch
fibery_mcp_server/tools/descriptions/create_entity
fibery_mcp_server/tools/descriptions/query
fibery_mcp_server/tools/descriptions/update_entity
fibery_mcp_server-0.1.4.dist-info/METADATA
fibery_mcp_server-0.1.4.dist-info/WHEEL
fibery_mcp_server-0.1.4.dist-info/entry_points.txt
fibery_mcp_server-0.1.4.dist-info/licenses/LICENSE
fibery_mcp_server-0.1.4.dist-info/RECORD
